setup.py
Flask_Dmango.egg-info/PKG-INFO
Flask_Dmango.egg-info/SOURCES.txt
Flask_Dmango.egg-info/dependency_links.txt
Flask_Dmango.egg-info/not-zip-safe
Flask_Dmango.egg-info/requires.txt
Flask_Dmango.egg-info/top_level.txt
flask_dmango/__init__.py
flask_dmango/dmango.py
flask_dmango/mongodb_helpers.py
flask_dmango/request_helpers.py
flask_dmango/query/__init__.py
flask_dmango/query/exceptions.py
flask_dmango/query/fields.py
flask_dmango/query/methods.py
flask_dmango/query/variables.py
flask_dmango/templates/__init__.py
flask_dmango/templates/admin/__init__.py
flask_dmango/templates/admin/authors.html
flask_dmango/templates/admin/collection.html
flask_dmango/templates/admin/contents_list.html
flask_dmango/templates/admin/detail.html
flask_dmango/templates/admin/edit.html
flask_dmango/templates/admin/index.html
flask_dmango/templates/admin/post.html
flask_dmango/templates/admin/templete.html
flask_dmango/templates/dmango/__init__.py
flask_dmango/templates/dmango/index.html
flask_dmango/view/__init__.py
flask_dmango/view/dmango_admin.py
flask_dmango/view/dmango_help.py
flask_dmango/view/dmango_restful.py
flask_dmango/view/view_decorators.py
sample/__init__.py
sample/ahn.py
sample/blueprint_find.py