Metadata-Version: 1.1
Name: Flask-Dmango
Version: 0.0.6
Summary: Contents managements support for Flask + MongoDB applications
Home-page: https://github.com/jungkoo/flask-dmango
Author: jeong mincheol
Author-email: deajang@gmail.com
License: BSD
Platform: any
Classifier: Environment :: Web Environment
Classifier: Intended Audience :: Developers
Classifier: License :: OSI Approved :: BSD License
Classifier: Operating System :: OS Independent
Classifier: Programming Language :: Python
Classifier: Programming Language :: Python :: 2.7
Classifier: Topic :: Internet :: WWW/HTTP :: Dynamic Content
Classifier: Topic :: Software Development :: Libraries :: Python Modules
